CaptchaCracker/__init__.py
CaptchaCracker/core.py
CaptchaCracker-0.0.7.dist-info/LICENSE
CaptchaCracker-0.0.7.dist-info/METADATA
CaptchaCracker-0.0.7.dist-info/WHEEL
CaptchaCracker-0.0.7.dist-info/top_level.txt
CaptchaCracker-0.0.7.dist-info/RECORD
