Metadata-Version: 2.1
Name: CaptchaCracker
Version: 0.0.7
Summary: CaptchaCracker is an open source Python library that provides functions to create and apply deep learning models for Captcha Image recognition.
Home-page: https://github.com/WooilJeong/CaptchaCracker
Author: Wooil Jeong
Author-email: wooil@kakao.com
License: MIT
Classifier: Programming Language :: Python :: 3
Classifier: License :: OSI Approved :: MIT License
Classifier: Operating System :: OS Independent
License-File: LICENSE
